{
  "analysis": "SeabornExploratoryEDA",
  "start_time_utc": "2026-04-16T14:59:31.504920Z",
  "end_time_utc": "2026-04-16T14:59:35.602548Z",
  "entries": [
    {
      "timestamp_utc": "2026-04-16T14:59:31.504976Z",
      "action": "INIT",
      "details": "Starting Seaborn EDA"
    },
    {
      "timestamp_utc": "2026-04-16T14:59:31.505000Z",
      "action": "DATA_LOAD",
      "details": "Loaded 10000 rows, 5 columns from Nielsen sample"
    },
    {
      "timestamp_utc": "2026-04-16T14:59:31.506996Z",
      "action": "STATISTICS",
      "details": "Computed 6 statistics"
    },
    {
      "timestamp_utc": "2026-04-16T14:59:34.233604Z",
      "action": "PLOT_DISTRIBUTIONS",
      "details": "Saved to seaborn_01_distributions.png"
    },
    {
      "timestamp_utc": "2026-04-16T14:59:35.083502Z",
      "action": "PLOT_RELATIONSHIPS",
      "details": "Saved to seaborn_02_relationships.png"
    },
    {
      "timestamp_utc": "2026-04-16T14:59:35.602493Z",
      "action": "PLOT_CORRELATION",
      "details": "Saved to seaborn_03_correlation.png"
    }
  ],
  "figures": [
    {
      "name": "distributions",
      "path": "C:\\Users\\brian\\OneDrive\\Documents\\02 - A - Areas\\MSc. Data Science\\2026-03 - CBS Master Thesis\\CMT_Codebase\\figures\\seaborn_exploratory\\seaborn_01_distributions.png",
      "timestamp_utc": "2026-04-16T14:59:34.233573Z"
    },
    {
      "name": "relationships",
      "path": "C:\\Users\\brian\\OneDrive\\Documents\\02 - A - Areas\\MSc. Data Science\\2026-03 - CBS Master Thesis\\CMT_Codebase\\figures\\seaborn_exploratory\\seaborn_02_relationships.png",
      "timestamp_utc": "2026-04-16T14:59:35.083473Z"
    },
    {
      "name": "correlation",
      "path": "C:\\Users\\brian\\OneDrive\\Documents\\02 - A - Areas\\MSc. Data Science\\2026-03 - CBS Master Thesis\\CMT_Codebase\\figures\\seaborn_exploratory\\seaborn_03_correlation.png",
      "timestamp_utc": "2026-04-16T14:59:35.602445Z"
    }
  ],
  "statistics": {
    "rows": 10000,
    "columns": 5,
    "missing_pct": 0.46,
    "demand_units_mean": 150.95688782299067,
    "demand_units_std": 93.70531428427675,
    "revenue_usd_mean": 190.26734640703606
  }
}